JoTools/__init__.py
JoTools/operateDeteRes.py
JoTools/for_csdn/find_same_img/find_same_img.py
JoTools/for_csdn/the_art_of_war/the_art_of_war.py
JoTools/for_csdn/the_art_of_war/data/the_art_of_war.txt
JoTools/for_csdn/the_art_of_war/data/the_art_of_war_line.txt
JoTools/for_csdn/word_pic/ucd_say.py
JoTools/for_csdn/word_pic/word_pic.py
JoTools/for_csdn/word_pic/data/del.pkl
JoTools/for_csdn/word_pic/data/word_analysis.pkl
JoTools/for_csdn/word_pic/data/word_analysis_2.pkl
JoTools/ml/__init__.py
JoTools/ml/deteOnnx.py
JoTools/txkj/__init__.py
JoTools/txkj/autoPS.py
JoTools/txkj/calMap.py
JoTools/txkj/calModelAcc.py
JoTools/txkj/configUtil.py
JoTools/txkj/draw_chart.py
JoTools/txkj/driveCudaTorch.py
JoTools/txkj/eagleUtil.py
JoTools/txkj/efficientDetDataset.py
JoTools/txkj/encryptFile.py
JoTools/txkj/encryptionModels.py
JoTools/txkj/fackImg.py
JoTools/txkj/findLinesFromPoints.py
JoTools/txkj/imageAugmentation.py
JoTools/txkj/jsonInfo.py
JoTools/txkj/parseXml.py
JoTools/txkj/segmentAndRegroup.py
JoTools/txkj/ucDatasetOpt.py
JoTools/txkj/ucDatasetUtil.py
JoTools/txkj/ucGenerator.py
JoTools/txkj/xml_to_yolo.py
JoTools/txkjRes/AllRes.py
JoTools/txkjRes/__init__.py
JoTools/txkjRes/configOpt.py
JoTools/txkjRes/deteAngleObj.py
JoTools/txkjRes/deteObj.py
JoTools/txkjRes/deteRes.py
JoTools/txkjRes/deteSegmentObj.py
JoTools/txkjRes/deteXml.py
JoTools/txkjRes/lineRes.py
JoTools/txkjRes/operateDeteRes.py
JoTools/txkjRes/parseJson.py
JoTools/txkjRes/pointRes.py
JoTools/txkjRes/pointXml.py
JoTools/txkjRes/postUtil.py
JoTools/txkjRes/receiveUtil.py
JoTools/txkjRes/resBase.py
JoTools/txkjRes/resTools.py
JoTools/txkjRes/segmentObj.py
JoTools/txkjRes/segmentRes.py
JoTools/utils/ArgparseUtil.py
JoTools/utils/BisectUtil.py
JoTools/utils/BlockUtil.py
JoTools/utils/BytesUtil.py
JoTools/utils/CompileUtil.py
JoTools/utils/CompressFolderUtil.py
JoTools/utils/ContextManagerUtil.py
JoTools/utils/CsvUtil.py
JoTools/utils/CtypeUtil.py
JoTools/utils/DecoratorUtil.py
JoTools/utils/DestructUtil.py
JoUtil-1.4.5.dist-info/METADATA
JoUtil-1.4.5.dist-info/WHEEL
JoUtil-1.4.5.dist-info/top_level.txt
JoUtil-1.4.5.dist-info/RECORD
