Metadata-Version: 2.1
Name: JoUtil
Version: 1.4.5
Summary: a tools for Saturn dete algo
Home-page: https://github.com/newjokker/JoUtil.git
Author: jokker
Author-email: 18761609908@163.com
Requires-Dist: numpy
Requires-Dist: pillow
Requires-Dist: pandas
Requires-Dist: easydict
Requires-Dist: matplotlib
Requires-Dist: imagehash
Requires-Dist: prettytable
Requires-Dist: progress
Requires-Dist: progressbar
Requires-Dist: requests
Requires-Dist: imageio
Requires-Dist: pyexiv2
Requires-Dist: opencv-python
Requires-Dist: exifread
Requires-Dist: whatimage
Requires-Dist: pyheif
Requires-Dist: pymysql
Requires-Dist: pytesseract
Requires-Dist: beautifulsoup4
Requires-Dist: Crypto
Requires-Dist: flask
Requires-Dist: shapely
